spacemake/alnstats.py
spacemake/reporting.py
spacemake_mjens-0.0.1.dist-info/METADATA
spacemake_mjens-0.0.1.dist-info/WHEEL
spacemake_mjens-0.0.1.dist-info/entry_points.txt
spacemake_mjens-0.0.1.dist-info/top_level.txt
spacemake_mjens-0.0.1.dist-info/RECORD
