Metadata-Version: 2.1
Name: spacemake-mjens
Version: 0.0.1
Summary: A bioinformatic pipeline for the analysis of spatial transcriptomic data
Home-page: https://github.com/rajewsky-lab/spacemake
Author: Nikolaos Karaiskos  Tamás Sztanka-Tóth  Marvin Jens
Author-email: TamasRyszard.Sztanka-Toth@mdc-berlin.de
License: MIT
Project-URL: Bug Tracker, https://github.com/rajewsky-lab/spacemake/issues
Platform: UNKNOWN
Classifier: Programming Language :: Python :: 3
Classifier: License :: OSI Approved :: MIT License
Classifier: Operating System :: OS Independent
Requires-Python: >=3.6
